LICENSE
MANIFEST.in
README.md
pyproject.toml
setup.py
tests/test.kvh
vkvh/__init__.py
vkvh/parcours.py
vkvh/version.txt
vkvh/vkvh.py
vkvh.egg-info/PKG-INFO
vkvh.egg-info/SOURCES.txt
vkvh.egg-info/dependency_links.txt
vkvh.egg-info/entry_points.txt
vkvh.egg-info/requires.txt
vkvh.egg-info/top_level.txt
vkvh/help/usage.html
vkvh/help/vkvh.hhc
vkvh/help/vkvh.hhp